passstrength142/__init__.py
passstrength142/password.py
passstrength142-1.0.0.dist-info/METADATA
passstrength142-1.0.0.dist-info/WHEEL
passstrength142-1.0.0.dist-info/top_level.txt
passstrength142-1.0.0.dist-info/RECORD
