Metadata-Version: 2.1
Name: passstrength142
Version: 1.0.0
Summary: A package for checking the strength of passwords and generating random passwords
Home-page: https://github.com/shri142/password-strength
Author: Shrikrishna Umbare
Author-email: shrikrishna2002umbare@gmail.com
License: UNKNOWN
Platform: UNKNOWN
Classifier: Development Status :: 5 - Production/Stable
Classifier: Intended Audience :: Developers
Classifier: Topic :: Security
Classifier: License :: OSI Approved :: MIT License
Classifier: Programming Language :: Python :: 3
Classifier: Programming Language :: Python :: 3.6
Classifier: Programming Language :: Python :: 3.7
Classifier: Programming Language :: Python :: 3.8
Classifier: Programming Language :: Python :: 3.9
Requires-Dist: requests
